__init__.py
examples/scripts/convert_to_ir.py
examples/scripts/data_dependency.py
examples/scripts/export_dominator_tree_to_dot.py
examples/scripts/export_to_dot.py
examples/scripts/functions_called.py
examples/scripts/functions_writing.py
examples/scripts/possible_paths.py
examples/scripts/slithIR.py
examples/scripts/taint_mapping.py
examples/scripts/variable_in_condition.py
plugin_example/setup.py
plugin_example/slither_my_plugin/__init__.py
plugin_example/slither_my_plugin/detectors/example.py
scripts/json_diff.py
slither/__about__.py
slither/__init__.py
slither/__main__.py
slither/all_exceptions.py
slither/exceptions.py
slither/slither.py
slither/analyses/__init__.py
slither/analyses/data_dependency/__init__.py
slither/analyses/data_dependency/data_dependency.py
slither/analyses/evm/__init__.py
slither/analyses/evm/convert.py
slither/analyses/evm/evm_cfg_builder.py
slither/analyses/write/__init__.py
slither/analyses/write/are_variables_written.py
slither/core/__init__.py
slither/core/compilation_unit.py
slither/core/exceptions.py
slither/core/slither_core.py
slither/core/cfg/__init__.py
slither/core/cfg/node.py
slither/core/cfg/scope.py
slither/core/children/__init__.py
slither/core/children/child_contract.py
slither/core/children/child_event.py
slither/core/children/child_expression.py
slither/core/children/child_function.py
slither/core/children/child_inheritance.py
slither/core/children/child_node.py
slither/core/children/child_structure.py
slither/core/context/__init__.py
slither/core/context/context.py
slither/core/declarations/__init__.py
slither/core/declarations/contract.py
slither/core/declarations/custom_error.py
slither/core/declarations/custom_error_contract.py
slither/core/declarations/custom_error_top_level.py
slither/core/declarations/enum.py
slither/core/declarations/enum_contract.py
slither/core/declarations/enum_top_level.py
slither/core/declarations/event.py
slither/core/declarations/function.py
slither/core/declarations/function_contract.py
slither_tcheck-0.1.0.dist-info/METADATA
slither_tcheck-0.1.0.dist-info/WHEEL
slither_tcheck-0.1.0.dist-info/licenses/LICENSE
slither_tcheck-0.1.0.dist-info/RECORD
