Metadata-Version: 2.1
Name: slither-tcheck
Version: 0.1.0
Summary: typechecking tool extension of slither
Project-URL: Documentation, https://github.com/NioTheFirst/SCTC-Full#readme
Project-URL: Issues, https://github.com/unknown/slither-tcheck/issues
Project-URL: Source, https://github.com/NioTheFirst/SCTC-Full
Author-email: NioTheFirst <bzhangprogramming@gmail.com>
License-Expression: MIT
License-File: LICENSE
Classifier: Development Status :: 4 - Beta
Classifier: Programming Language :: Python
Classifier: Programming Language :: Python :: 3.7
Classifier: Programming Language :: Python :: 3.8
Classifier: Programming Language :: Python :: 3.9
Classifier: Programming Language :: Python :: 3.10
Classifier: Programming Language :: Python :: 3.11
Classifier: Programming Language :: Python :: Implementation :: CPython
Classifier: Programming Language :: Python :: Implementation :: PyPy
Requires-Python: >=3.7
Requires-Dist: argparse>=1.4.0
Requires-Dist: slither-analyzer>=0.9.0
Requires-Dist: solc-select>=1.0.0
Requires-Dist: z3-solver>=4.10
